{
  "modelName": "New Model",
  "collections": [
    {
      "collectionName": "New Document",
      "type": "object",
      "properties": [
        {
          "name": "New Field",
          "hackoladeMeta": {},
          "isActivated": true,
          "type": "string",
          "properties": [],
          "GUID": "087fafb1-531c-425c-a244-7097d758f1eb",
          "error": {
            "name": false,
            "code": false
          }
        },
        {
          "name": "New Field1",
          "hackoladeMeta": {},
          "isActivated": true,
          "type": "string",
          "properties": [],
          "GUID": "0ae4061d-85a7-4c25-bb70-201b3eb3c680",
          "error": {
            "name": false,
            "code": false
          }
        },
        {
          "name": "New Field2",
          "hackoladeMeta": {},
          "isActivated": true,
          "type": "string",
          "properties": [],
          "GUID": "6663be51-9fac-4564-8e3b-5f84d35d240b",
          "error": {
            "name": false,
            "code": false
          }
        }
      ],
      "definitions": {
        "type": "definitions",
        "properties": [],
        "GUID": "db7c8410-7e21-4852-894e-2b13fe4576e4"
      },
      "isActivated": true,
      "additionalProperties": false,
      "GUID": "97f42135-c36d-49c8-aa93-56290c102d21"
    }
  ],
  "buckets": [],
  "views": [],
  "relationships": [],
  "users": [],
  "diagramViews": [],
  "idToNameHashTable": {
    "97f42135-c36d-49c8-aa93-56290c102d21": "New Document",
    "087fafb1-531c-425c-a244-7097d758f1eb": "New Field",
    "0ae4061d-85a7-4c25-bb70-201b3eb3c680": "New Field1",
    "6663be51-9fac-4564-8e3b-5f84d35d240b": "New Field2"
  },
  "definitions": {
    "type": "definitions",
    "properties": [],
    "GUID": "01f77c4d-2084-4adb-a2ea-f8763a340ac9"
  },
  "polyglotDefinitions": {
    "type": "polyglotDefinitions",
    "properties": [],
    "GUID": "441dcbb9-cac9-432f-9070-c73df9b18552"
  },
  "externalDefinitions": {
    "type": "externalDefinitions",
    "properties": [],
    "GUID": "282d5199-51dd-4dbd-9755-cff9a3f7181b"
  },
  "sources": [],
  "decorativeSymbols": [],
  "dbVendor": "JSON",
  "dbVersion": "2019-09",
  "appTarget": "JSON",
  "creationTS": "2025-10-28T14:24:19.504Z",
  "GUID": "e0c4f3a5-694e-4914-9018-89baddbaffa6",
  "isLineageEnabled": false,
  "lastModifTS": "2025-10-28T14:24:44.631Z",
  "persistenceSchemaVersion": "8",
  "isCreatedByPlugin": true,
  "pluginInformation": {
    "pluginEngineVersion": "1.0.0"
  },
  "applicationInformation": {
    "version": "8.5.4"
  },
  "settings": {
    "centralPane": {
      "dbLevel": {
        "erd": [
          {
            "GUID": "97f42135-c36d-49c8-aa93-56290c102d21",
            "x": 2341,
            "y": 1455,
            "width": 208,
            "height": 86,
            "color": {}
          }
        ],
        "erdDefinitions": {
          "erd": [],
          "rootPath": [],
          "entities": [],
          "decorativeSymbols": []
        },
        "buckets": [],
        "collapsedNodes": [],
        "activeRelationship": "",
        "activeRelationshipFields": {
          "childField": [],
          "parentField": []
        },
        "selectedCollections": [],
        "displayColorPicker": false,
        "graphView": {
          "erd": [],
          "buckets": [],
          "decorativeSymbols": [],
          "forceLayout": true,
          "defaultLinkLength": 300
        },
        "diagramViews": [],
        "decorativeSymbols": [],
        "nestedCollectionsLayout": "horizontal",
        "options": [],
        "relationshipUpdateDisabled": false
      },
      "collectionLevel": {},
      "changed": false
    },
    "dtDiagram": {
      "collapsedNodes": [],
      "shouldDistributeCollections": false
    }
  }
}